embasp/__init__.py
embasp/base/__init__.py
embasp/base/callback.py
embasp/base/handler.py
embasp/base/input_program.py
embasp/base/option_descriptor.py
embasp/base/output.py
embasp/base/service.py
embasp/languages/__init__.py
embasp/languages/mapper.py
embasp/languages/predicate.py
embasp/languages/asp/__init__.py
embasp/languages/asp/answer_set.py
embasp/languages/asp/answer_sets.py
embasp/languages/asp/asp_filter_option.py
embasp/languages/asp/asp_input_program.py
embasp/languages/asp/asp_mapper.py
embasp/languages/asp/symbolic_constant.py
embasp/languages/datalog/__init__.py
embasp/languages/datalog/datalog_input_program.py
embasp/languages/datalog/datalog_mapper.py
embasp/languages/datalog/minimal_model.py
embasp/languages/datalog/minimal_models.py
embasp/languages/pddl/__init__.py
embasp/languages/pddl/action.py
embasp/languages/pddl/pddl_exception.py
embasp/languages/pddl/pddl_input_program.py
embasp/languages/pddl/pddl_mapper.py
embasp/languages/pddl/pddl_program_type.py
embasp/languages/pddl/plan.py
embasp/platforms/__init__.py
embasp/platforms/desktop/__init__.py
embasp/platforms/desktop/desktop_handler.py
embasp/platforms/desktop/desktop_service.py
embasp/specializations/__init__.py
embasp/specializations/clingo/__init__.py
embasp/specializations/clingo/clingo_answer_sets.py
embasp/specializations/clingo/desktop/__init__.py
embasp/specializations/clingo/desktop/clingo_desktop_service.py
embasp/specializations/dlv/__init__.py
embasp/specializations/dlv/dlv_answer_sets.py
embasp/specializations/dlv/dlv_filter_option.py
embasp/specializations/dlv/desktop/__init__.py
embasp/specializations/dlv/desktop/dlv_desktop_service.py
embasp/specializations/dlv2/__init__.py
embasp/specializations/dlv2/dlv2_answer_sets.py
embasp/specializations/dlv2/desktop/__init__.py
embasp/specializations/dlv2/desktop/dlv2_desktop_service.py
embasp/specializations/dlvhex/__init__.py
embasp/specializations/dlvhex/dlvhex_answer_sets.py
embasp/specializations/dlvhex/desktop/__init__.py
embasp_python-8.1.3.dist-info/LICENSE
embasp_python-8.1.3.dist-info/METADATA
embasp_python-8.1.3.dist-info/WHEEL
embasp_python-8.1.3.dist-info/top_level.txt
embasp_python-8.1.3.dist-info/RECORD
