Metadata-Version: 2.1
Name: embasp-python
Version: 8.1.3
Summary: EmbASP is a framework for the integration of Logic Programming in external systems
Home-page: https://www.mat.unical.it/calimeri/projects/embasp/
Author: Department of Mathematics and Computer Science, University of Calabria
Author-email: embasp@mat.unical.it
License: MIT License
Project-URL: Homepage, https://www.mat.unical.it/calimeri/projects/embasp
Classifier: Development Status :: 5 - Production/Stable
Classifier: License :: OSI Approved :: MIT License
Classifier: Programming Language :: Python :: 3
Classifier: Programming Language :: Python :: 2
License-File: LICENSE
Requires-Dist: antlr4-python3-runtime ==4.7
